<?xml version="1.0" encoding="UTF-8"?>
<!DOCTYPE mapper PUBLIC "-//mybatis.org//DTD Mapper 3.0//EN" "http://mybatis.org/dtd/mybatis-3-mapper.dtd">
<mapper namespace="job.sfcommon.dataaccess.mapper.looponexcore.SlgTagMasterMapper">
  <resultMap id="BaseResultMap" type="job.sfcommon.dataaccess.entity.looponexcore.SlgTagMaster">
    <!--
      WARNING - @mbg.generated
      This element is automatically generated by MyBatis Generator, do not modify.
    -->
    <id column="lcode" jdbcType="VARCHAR" property="lcode" />
    <result column="disp_order" jdbcType="INTEGER" property="dispOrder" />
    <result column="dcs_tag_item" jdbcType="VARCHAR" property="dcsTagItem" />
    <result column="comment1" jdbcType="VARCHAR" property="comment1" />
    <result column="stn_name" jdbcType="VARCHAR" property="stnName" />
    <result column="unit_dcs" jdbcType="VARCHAR" property="unitDcs" />
    <result column="unit_computer" jdbcType="VARCHAR" property="unitComputer" />
    <result column="multiplier" jdbcType="INTEGER" property="multiplier" />
    <result column="dp" jdbcType="INTEGER" property="dp" />
    <result column="upper_value" jdbcType="DOUBLE" property="upperValue" />
    <result column="lower_value" jdbcType="DOUBLE" property="lowerValue" />
    <result column="csxl" jdbcType="VARCHAR" property="csxl" />
    <result column="collect_group_no" jdbcType="INTEGER" property="collectGroupNo" />
    <result column="history_group_no" jdbcType="INTEGER" property="historyGroupNo" />
    <result column="lastvalue_hold_flag" jdbcType="INTEGER" property="lastvalueHoldFlag" />
    <result column="collect_stop_flag" jdbcType="INTEGER" property="collectStopFlag" />
    <result column="note1" jdbcType="VARCHAR" property="note1" />
    <result column="note2" jdbcType="VARCHAR" property="note2" />
    <result column="note3" jdbcType="VARCHAR" property="note3" />
    <result column="note4" jdbcType="VARCHAR" property="note4" />
    <result column="note5" jdbcType="VARCHAR" property="note5" />
    <result column="note6" jdbcType="VARCHAR" property="note6" />
    <result column="note7" jdbcType="VARCHAR" property="note7" />
    <result column="note8" jdbcType="VARCHAR" property="note8" />
    <result column="note9" jdbcType="VARCHAR" property="note9" />
    <result column="note10" jdbcType="VARCHAR" property="note10" />
    <result column="start_address" jdbcType="INTEGER" property="startAddress" />
    <result column="modbus_data_type" jdbcType="VARCHAR" property="modbusDataType" />
    <result column="modbus_string_size" jdbcType="INTEGER" property="modbusStringSize" />
    <result column="hi" jdbcType="DOUBLE" property="hi" />
    <result column="lo" jdbcType="DOUBLE" property="lo" />
    <result column="rate_change_flag" jdbcType="INTEGER" property="rateChangeFlag" />
    <result column="change_volume" jdbcType="DOUBLE" property="changeVolume" />
    <result column="hh" jdbcType="DOUBLE" property="hh" />
    <result column="ll" jdbcType="DOUBLE" property="ll" />
    <result column="alert_message" jdbcType="VARCHAR" property="alertMessage" />
    <result column="check_cycle" jdbcType="VARCHAR" property="checkCycle" />
    <result column="contact_group" jdbcType="VARCHAR" property="contactGroup" />
    <result column="mail_body" jdbcType="VARCHAR" property="mailBody" />
    <result column="alert_tag" jdbcType="VARCHAR" property="alertTag" />
    <result column="create_person" jdbcType="CHAR" property="createPerson" />
    <result column="create_date" jdbcType="TIMESTAMP" property="createDate" />
    <result column="update_person" jdbcType="CHAR" property="updatePerson" />
    <result column="update_date" jdbcType="TIMESTAMP" property="updateDate" />
  </resultMap>
  <sql id="Example_Where_Clause">
    <!--
      WARNING - @mbg.generated
      This element is automatically generated by MyBatis Generator, do not modify.
    -->
    <where>
      <foreach collection="oredCriteria" item="criteria" separator="or">
        <if test="criteria.valid">
          <trim prefix="(" prefixOverrides="and" suffix=")">
            <foreach collection="criteria.criteria" item="criterion">
              <choose>
                <when test="criterion.noValue">
                  and ${criterion.condition}
                </when>
                <when test="criterion.singleValue">
                  and ${criterion.condition} #{criterion.value}
                </when>
                <when test="criterion.betweenValue">
                  and ${criterion.condition} #{criterion.value} and #{criterion.secondValue}
                </when>
                <when test="criterion.listValue">
                  and ${criterion.condition}
                  <foreach close=")" collection="criterion.value" item="listItem" open="(" separator=",">
                    #{listItem}
                  </foreach>
                </when>
              </choose>
            </foreach>
          </trim>
        </if>
      </foreach>
    </where>
  </sql>
  <sql id="Update_By_Example_Where_Clause">
    <!--
      WARNING - @mbg.generated
      This element is automatically generated by MyBatis Generator, do not modify.
    -->
    <where>
      <foreach collection="example.oredCriteria" item="criteria" separator="or">
        <if test="criteria.valid">
          <trim prefix="(" prefixOverrides="and" suffix=")">
            <foreach collection="criteria.criteria" item="criterion">
              <choose>
                <when test="criterion.noValue">
                  and ${criterion.condition}
                </when>
                <when test="criterion.singleValue">
                  and ${criterion.condition} #{criterion.value}
                </when>
                <when test="criterion.betweenValue">
                  and ${criterion.condition} #{criterion.value} and #{criterion.secondValue}
                </when>
                <when test="criterion.listValue">
                  and ${criterion.condition}
                  <foreach close=")" collection="criterion.value" item="listItem" open="(" separator=",">
                    #{listItem}
                  </foreach>
                </when>
              </choose>
            </foreach>
          </trim>
        </if>
      </foreach>
    </where>
  </sql>
  <sql id="Base_Column_List">
    <!--
      WARNING - @mbg.generated
      This element is automatically generated by MyBatis Generator, do not modify.
    -->
    lcode, disp_order, dcs_tag_item, comment1, stn_name, unit_dcs, unit_computer, multiplier, 
    dp, upper_value, lower_value, csxl, collect_group_no, history_group_no, lastvalue_hold_flag, 
    collect_stop_flag, note1, note2, note3, note4, note5, note6, note7, note8, note9, 
    note10, start_address, modbus_data_type, modbus_string_size, hi, lo, rate_change_flag, 
    change_volume, hh, ll, alert_message, check_cycle, contact_group, mail_body, alert_tag, 
    create_person, create_date, update_person, update_date
  </sql>
  <select id="selectByExample" parameterType="job.sfcommon.dataaccess.entity.looponexcore.SlgTagMasterExample" resultMap="BaseResultMap">
    <!--
      WARNING - @mbg.generated
      This element is automatically generated by MyBatis Generator, do not modify.
    -->
    select
    <if test="distinct">
      distinct
    </if>
    <include refid="Base_Column_List" />
    from public.slg_tag_master
    <if test="_parameter != null">
      <include refid="Example_Where_Clause" />
    </if>
    <if test="orderByClause != null">
      order by ${orderByClause}
    </if>
  </select>
  <select id="selectByPrimaryKey" parameterType="java.lang.String" resultMap="BaseResultMap">
    <!--
      WARNING - @mbg.generated
      This element is automatically generated by MyBatis Generator, do not modify.
    -->
    select 
    <include refid="Base_Column_List" />
    from public.slg_tag_master
    where lcode = #{lcode,jdbcType=VARCHAR}
  </select>
  <delete id="deleteByPrimaryKey" parameterType="java.lang.String">
    <!--
      WARNING - @mbg.generated
      This element is automatically generated by MyBatis Generator, do not modify.
    -->
    delete from public.slg_tag_master
    where lcode = #{lcode,jdbcType=VARCHAR}
  </delete>
  <delete id="deleteByExample" parameterType="job.sfcommon.dataaccess.entity.looponexcore.SlgTagMasterExample">
    <!--
      WARNING - @mbg.generated
      This element is automatically generated by MyBatis Generator, do not modify.
    -->
    delete from public.slg_tag_master
    <if test="_parameter != null">
      <include refid="Example_Where_Clause" />
    </if>
  </delete>
  <insert id="insert" parameterType="job.sfcommon.dataaccess.entity.looponexcore.SlgTagMaster">
    <!--
      WARNING - @mbg.generated
      This element is automatically generated by MyBatis Generator, do not modify.
    -->
    insert into public.slg_tag_master (lcode, disp_order, dcs_tag_item, 
      comment1, stn_name, unit_dcs, 
      unit_computer, multiplier, dp, 
      upper_value, lower_value, csxl, 
      collect_group_no, history_group_no, lastvalue_hold_flag, 
      collect_stop_flag, note1, note2, 
      note3, note4, note5, 
      note6, note7, note8, 
      note9, note10, start_address, 
      modbus_data_type, modbus_string_size, hi, 
      lo, rate_change_flag, change_volume, 
      hh, ll, alert_message, 
      check_cycle, contact_group, mail_body, 
      alert_tag, create_person, create_date, 
      update_person, update_date)
    values (#{lcode,jdbcType=VARCHAR}, #{dispOrder,jdbcType=INTEGER}, #{dcsTagItem,jdbcType=VARCHAR}, 
      #{comment1,jdbcType=VARCHAR}, #{stnName,jdbcType=VARCHAR}, #{unitDcs,jdbcType=VARCHAR}, 
      #{unitComputer,jdbcType=VARCHAR}, #{multiplier,jdbcType=INTEGER}, #{dp,jdbcType=INTEGER}, 
      #{upperValue,jdbcType=DOUBLE}, #{lowerValue,jdbcType=DOUBLE}, #{csxl,jdbcType=VARCHAR}, 
      #{collectGroupNo,jdbcType=INTEGER}, #{historyGroupNo,jdbcType=INTEGER}, #{lastvalueHoldFlag,jdbcType=INTEGER}, 
      #{collectStopFlag,jdbcType=INTEGER}, #{note1,jdbcType=VARCHAR}, #{note2,jdbcType=VARCHAR}, 
      #{note3,jdbcType=VARCHAR}, #{note4,jdbcType=VARCHAR}, #{note5,jdbcType=VARCHAR}, 
      #{note6,jdbcType=VARCHAR}, #{note7,jdbcType=VARCHAR}, #{note8,jdbcType=VARCHAR}, 
      #{note9,jdbcType=VARCHAR}, #{note10,jdbcType=VARCHAR}, #{startAddress,jdbcType=INTEGER}, 
      #{modbusDataType,jdbcType=VARCHAR}, #{modbusStringSize,jdbcType=INTEGER}, #{hi,jdbcType=DOUBLE}, 
      #{lo,jdbcType=DOUBLE}, #{rateChangeFlag,jdbcType=INTEGER}, #{changeVolume,jdbcType=DOUBLE}, 
      #{hh,jdbcType=DOUBLE}, #{ll,jdbcType=DOUBLE}, #{alertMessage,jdbcType=VARCHAR}, 
      #{checkCycle,jdbcType=VARCHAR}, #{contactGroup,jdbcType=VARCHAR}, #{mailBody,jdbcType=VARCHAR}, 
      #{alertTag,jdbcType=VARCHAR}, #{createPerson,jdbcType=CHAR}, #{createDate,jdbcType=TIMESTAMP}, 
      #{updatePerson,jdbcType=CHAR}, #{updateDate,jdbcType=TIMESTAMP})
  </insert>
  <insert id="insertSelective" parameterType="job.sfcommon.dataaccess.entity.looponexcore.SlgTagMaster">
    <!--
      WARNING - @mbg.generated
      This element is automatically generated by MyBatis Generator, do not modify.
    -->
    insert into public.slg_tag_master
    <trim prefix="(" suffix=")" suffixOverrides=",">
      <if test="lcode != null">
        lcode,
      </if>
      <if test="dispOrder != null">
        disp_order,
      </if>
      <if test="dcsTagItem != null">
        dcs_tag_item,
      </if>
      <if test="comment1 != null">
        comment1,
      </if>
      <if test="stnName != null">
        stn_name,
      </if>
      <if test="unitDcs != null">
        unit_dcs,
      </if>
      <if test="unitComputer != null">
        unit_computer,
      </if>
      <if test="multiplier != null">
        multiplier,
      </if>
      <if test="dp != null">
        dp,
      </if>
      <if test="upperValue != null">
        upper_value,
      </if>
      <if test="lowerValue != null">
        lower_value,
      </if>
      <if test="csxl != null">
        csxl,
      </if>
      <if test="collectGroupNo != null">
        collect_group_no,
      </if>
      <if test="historyGroupNo != null">
        history_group_no,
      </if>
      <if test="lastvalueHoldFlag != null">
        lastvalue_hold_flag,
      </if>
      <if test="collectStopFlag != null">
        collect_stop_flag,
      </if>
      <if test="note1 != null">
        note1,
      </if>
      <if test="note2 != null">
        note2,
      </if>
      <if test="note3 != null">
        note3,
      </if>
      <if test="note4 != null">
        note4,
      </if>
      <if test="note5 != null">
        note5,
      </if>
      <if test="note6 != null">
        note6,
      </if>
      <if test="note7 != null">
        note7,
      </if>
      <if test="note8 != null">
        note8,
      </if>
      <if test="note9 != null">
        note9,
      </if>
      <if test="note10 != null">
        note10,
      </if>
      <if test="startAddress != null">
        start_address,
      </if>
      <if test="modbusDataType != null">
        modbus_data_type,
      </if>
      <if test="modbusStringSize != null">
        modbus_string_size,
      </if>
      <if test="hi != null">
        hi,
      </if>
      <if test="lo != null">
        lo,
      </if>
      <if test="rateChangeFlag != null">
        rate_change_flag,
      </if>
      <if test="changeVolume != null">
        change_volume,
      </if>
      <if test="hh != null">
        hh,
      </if>
      <if test="ll != null">
        ll,
      </if>
      <if test="alertMessage != null">
        alert_message,
      </if>
      <if test="checkCycle != null">
        check_cycle,
      </if>
      <if test="contactGroup != null">
        contact_group,
      </if>
      <if test="mailBody != null">
        mail_body,
      </if>
      <if test="alertTag != null">
        alert_tag,
      </if>
      <if test="createPerson != null">
        create_person,
      </if>
      <if test="createDate != null">
        create_date,
      </if>
      <if test="updatePerson != null">
        update_person,
      </if>
      <if test="updateDate != null">
        update_date,
      </if>
    </trim>
    <trim prefix="values (" suffix=")" suffixOverrides=",">
      <if test="lcode != null">
        #{lcode,jdbcType=VARCHAR},
      </if>
      <if test="dispOrder != null">
        #{dispOrder,jdbcType=INTEGER},
      </if>
      <if test="dcsTagItem != null">
        #{dcsTagItem,jdbcType=VARCHAR},
      </if>
      <if test="comment1 != null">
        #{comment1,jdbcType=VARCHAR},
      </if>
      <if test="stnName != null">
        #{stnName,jdbcType=VARCHAR},
      </if>
      <if test="unitDcs != null">
        #{unitDcs,jdbcType=VARCHAR},
      </if>
      <if test="unitComputer != null">
        #{unitComputer,jdbcType=VARCHAR},
      </if>
      <if test="multiplier != null">
        #{multiplier,jdbcType=INTEGER},
      </if>
      <if test="dp != null">
        #{dp,jdbcType=INTEGER},
      </if>
      <if test="upperValue != null">
        #{upperValue,jdbcType=DOUBLE},
      </if>
      <if test="lowerValue != null">
        #{lowerValue,jdbcType=DOUBLE},
      </if>
      <if test="csxl != null">
        #{csxl,jdbcType=VARCHAR},
      </if>
      <if test="collectGroupNo != null">
        #{collectGroupNo,jdbcType=INTEGER},
      </if>
      <if test="historyGroupNo != null">
        #{historyGroupNo,jdbcType=INTEGER},
      </if>
      <if test="lastvalueHoldFlag != null">
        #{lastvalueHoldFlag,jdbcType=INTEGER},
      </if>
      <if test="collectStopFlag != null">
        #{collectStopFlag,jdbcType=INTEGER},
      </if>
      <if test="note1 != null">
        #{note1,jdbcType=VARCHAR},
      </if>
      <if test="note2 != null">
        #{note2,jdbcType=VARCHAR},
      </if>
      <if test="note3 != null">
        #{note3,jdbcType=VARCHAR},
      </if>
      <if test="note4 != null">
        #{note4,jdbcType=VARCHAR},
      </if>
      <if test="note5 != null">
        #{note5,jdbcType=VARCHAR},
      </if>
      <if test="note6 != null">
        #{note6,jdbcType=VARCHAR},
      </if>
      <if test="note7 != null">
        #{note7,jdbcType=VARCHAR},
      </if>
      <if test="note8 != null">
        #{note8,jdbcType=VARCHAR},
      </if>
      <if test="note9 != null">
        #{note9,jdbcType=VARCHAR},
      </if>
      <if test="note10 != null">
        #{note10,jdbcType=VARCHAR},
      </if>
      <if test="startAddress != null">
        #{startAddress,jdbcType=INTEGER},
      </if>
      <if test="modbusDataType != null">
        #{modbusDataType,jdbcType=VARCHAR},
      </if>
      <if test="modbusStringSize != null">
        #{modbusStringSize,jdbcType=INTEGER},
      </if>
      <if test="hi != null">
        #{hi,jdbcType=DOUBLE},
      </if>
      <if test="lo != null">
        #{lo,jdbcType=DOUBLE},
      </if>
      <if test="rateChangeFlag != null">
        #{rateChangeFlag,jdbcType=INTEGER},
      </if>
      <if test="changeVolume != null">
        #{changeVolume,jdbcType=DOUBLE},
      </if>
      <if test="hh != null">
        #{hh,jdbcType=DOUBLE},
      </if>
      <if test="ll != null">
        #{ll,jdbcType=DOUBLE},
      </if>
      <if test="alertMessage != null">
        #{alertMessage,jdbcType=VARCHAR},
      </if>
      <if test="checkCycle != null">
        #{checkCycle,jdbcType=VARCHAR},
      </if>
      <if test="contactGroup != null">
        #{contactGroup,jdbcType=VARCHAR},
      </if>
      <if test="mailBody != null">
        #{mailBody,jdbcType=VARCHAR},
      </if>
      <if test="alertTag != null">
        #{alertTag,jdbcType=VARCHAR},
      </if>
      <if test="createPerson != null">
        #{createPerson,jdbcType=CHAR},
      </if>
      <if test="createDate != null">
        #{createDate,jdbcType=TIMESTAMP},
      </if>
      <if test="updatePerson != null">
        #{updatePerson,jdbcType=CHAR},
      </if>
      <if test="updateDate != null">
        #{updateDate,jdbcType=TIMESTAMP},
      </if>
    </trim>
  </insert>
  <select id="countByExample" parameterType="job.sfcommon.dataaccess.entity.looponexcore.SlgTagMasterExample" resultType="java.lang.Long">
    <!--
      WARNING - @mbg.generated
      This element is automatically generated by MyBatis Generator, do not modify.
    -->
    select count(*) from public.slg_tag_master
    <if test="_parameter != null">
      <include refid="Example_Where_Clause" />
    </if>
  </select>
  <update id="updateByExampleSelective" parameterType="map">
    <!--
      WARNING - @mbg.generated
      This element is automatically generated by MyBatis Generator, do not modify.
    -->
    update public.slg_tag_master
    <set>
      <if test="record.lcode != null">
        lcode = #{record.lcode,jdbcType=VARCHAR},
      </if>
      <if test="record.dispOrder != null">
        disp_order = #{record.dispOrder,jdbcType=INTEGER},
      </if>
      <if test="record.dcsTagItem != null">
        dcs_tag_item = #{record.dcsTagItem,jdbcType=VARCHAR},
      </if>
      <if test="record.comment1 != null">
        comment1 = #{record.comment1,jdbcType=VARCHAR},
      </if>
      <if test="record.stnName != null">
        stn_name = #{record.stnName,jdbcType=VARCHAR},
      </if>
      <if test="record.unitDcs != null">
        unit_dcs = #{record.unitDcs,jdbcType=VARCHAR},
      </if>
      <if test="record.unitComputer != null">
        unit_computer = #{record.unitComputer,jdbcType=VARCHAR},
      </if>
      <if test="record.multiplier != null">
        multiplier = #{record.multiplier,jdbcType=INTEGER},
      </if>
      <if test="record.dp != null">
        dp = #{record.dp,jdbcType=INTEGER},
      </if>
      <if test="record.upperValue != null">
        upper_value = #{record.upperValue,jdbcType=DOUBLE},
      </if>
      <if test="record.lowerValue != null">
        lower_value = #{record.lowerValue,jdbcType=DOUBLE},
      </if>
      <if test="record.csxl != null">
        csxl = #{record.csxl,jdbcType=VARCHAR},
      </if>
      <if test="record.collectGroupNo != null">
        collect_group_no = #{record.collectGroupNo,jdbcType=INTEGER},
      </if>
      <if test="record.historyGroupNo != null">
        history_group_no = #{record.historyGroupNo,jdbcType=INTEGER},
      </if>
      <if test="record.lastvalueHoldFlag != null">
        lastvalue_hold_flag = #{record.lastvalueHoldFlag,jdbcType=INTEGER},
      </if>
      <if test="record.collectStopFlag != null">
        collect_stop_flag = #{record.collectStopFlag,jdbcType=INTEGER},
      </if>
      <if test="record.note1 != null">
        note1 = #{record.note1,jdbcType=VARCHAR},
      </if>
      <if test="record.note2 != null">
        note2 = #{record.note2,jdbcType=VARCHAR},
      </if>
      <if test="record.note3 != null">
        note3 = #{record.note3,jdbcType=VARCHAR},
      </if>
      <if test="record.note4 != null">
        note4 = #{record.note4,jdbcType=VARCHAR},
      </if>
      <if test="record.note5 != null">
        note5 = #{record.note5,jdbcType=VARCHAR},
      </if>
      <if test="record.note6 != null">
        note6 = #{record.note6,jdbcType=VARCHAR},
      </if>
      <if test="record.note7 != null">
        note7 = #{record.note7,jdbcType=VARCHAR},
      </if>
      <if test="record.note8 != null">
        note8 = #{record.note8,jdbcType=VARCHAR},
      </if>
      <if test="record.note9 != null">
        note9 = #{record.note9,jdbcType=VARCHAR},
      </if>
      <if test="record.note10 != null">
        note10 = #{record.note10,jdbcType=VARCHAR},
      </if>
      <if test="record.startAddress != null">
        start_address = #{record.startAddress,jdbcType=INTEGER},
      </if>
      <if test="record.modbusDataType != null">
        modbus_data_type = #{record.modbusDataType,jdbcType=VARCHAR},
      </if>
      <if test="record.modbusStringSize != null">
        modbus_string_size = #{record.modbusStringSize,jdbcType=INTEGER},
      </if>
      <if test="record.hi != null">
        hi = #{record.hi,jdbcType=DOUBLE},
      </if>
      <if test="record.lo != null">
        lo = #{record.lo,jdbcType=DOUBLE},
      </if>
      <if test="record.rateChangeFlag != null">
        rate_change_flag = #{record.rateChangeFlag,jdbcType=INTEGER},
      </if>
      <if test="record.changeVolume != null">
        change_volume = #{record.changeVolume,jdbcType=DOUBLE},
      </if>
      <if test="record.hh != null">
        hh = #{record.hh,jdbcType=DOUBLE},
      </if>
      <if test="record.ll != null">
        ll = #{record.ll,jdbcType=DOUBLE},
      </if>
      <if test="record.alertMessage != null">
        alert_message = #{record.alertMessage,jdbcType=VARCHAR},
      </if>
      <if test="record.checkCycle != null">
        check_cycle = #{record.checkCycle,jdbcType=VARCHAR},
      </if>
      <if test="record.contactGroup != null">
        contact_group = #{record.contactGroup,jdbcType=VARCHAR},
      </if>
      <if test="record.mailBody != null">
        mail_body = #{record.mailBody,jdbcType=VARCHAR},
      </if>
      <if test="record.alertTag != null">
        alert_tag = #{record.alertTag,jdbcType=VARCHAR},
      </if>
      <if test="record.createPerson != null">
        create_person = #{record.createPerson,jdbcType=CHAR},
      </if>
      <if test="record.createDate != null">
        create_date = #{record.createDate,jdbcType=TIMESTAMP},
      </if>
      <if test="record.updatePerson != null">
        update_person = #{record.updatePerson,jdbcType=CHAR},
      </if>
      <if test="record.updateDate != null">
        update_date = #{record.updateDate,jdbcType=TIMESTAMP},
      </if>
    </set>
    <if test="_parameter != null">
      <include refid="Update_By_Example_Where_Clause" />
    </if>
  </update>
  <update id="updateByExample" parameterType="map">
    <!--
      WARNING - @mbg.generated
      This element is automatically generated by MyBatis Generator, do not modify.
    -->
    update public.slg_tag_master
    set lcode = #{record.lcode,jdbcType=VARCHAR},
      disp_order = #{record.dispOrder,jdbcType=INTEGER},
      dcs_tag_item = #{record.dcsTagItem,jdbcType=VARCHAR},
      comment1 = #{record.comment1,jdbcType=VARCHAR},
      stn_name = #{record.stnName,jdbcType=VARCHAR},
      unit_dcs = #{record.unitDcs,jdbcType=VARCHAR},
      unit_computer = #{record.unitComputer,jdbcType=VARCHAR},
      multiplier = #{record.multiplier,jdbcType=INTEGER},
      dp = #{record.dp,jdbcType=INTEGER},
      upper_value = #{record.upperValue,jdbcType=DOUBLE},
      lower_value = #{record.lowerValue,jdbcType=DOUBLE},
      csxl = #{record.csxl,jdbcType=VARCHAR},
      collect_group_no = #{record.collectGroupNo,jdbcType=INTEGER},
      history_group_no = #{record.historyGroupNo,jdbcType=INTEGER},
      lastvalue_hold_flag = #{record.lastvalueHoldFlag,jdbcType=INTEGER},
      collect_stop_flag = #{record.collectStopFlag,jdbcType=INTEGER},
      note1 = #{record.note1,jdbcType=VARCHAR},
      note2 = #{record.note2,jdbcType=VARCHAR},
      note3 = #{record.note3,jdbcType=VARCHAR},
      note4 = #{record.note4,jdbcType=VARCHAR},
      note5 = #{record.note5,jdbcType=VARCHAR},
      note6 = #{record.note6,jdbcType=VARCHAR},
      note7 = #{record.note7,jdbcType=VARCHAR},
      note8 = #{record.note8,jdbcType=VARCHAR},
      note9 = #{record.note9,jdbcType=VARCHAR},
      note10 = #{record.note10,jdbcType=VARCHAR},
      start_address = #{record.startAddress,jdbcType=INTEGER},
      modbus_data_type = #{record.modbusDataType,jdbcType=VARCHAR},
      modbus_string_size = #{record.modbusStringSize,jdbcType=INTEGER},
      hi = #{record.hi,jdbcType=DOUBLE},
      lo = #{record.lo,jdbcType=DOUBLE},
      rate_change_flag = #{record.rateChangeFlag,jdbcType=INTEGER},
      change_volume = #{record.changeVolume,jdbcType=DOUBLE},
      hh = #{record.hh,jdbcType=DOUBLE},
      ll = #{record.ll,jdbcType=DOUBLE},
      alert_message = #{record.alertMessage,jdbcType=VARCHAR},
      check_cycle = #{record.checkCycle,jdbcType=VARCHAR},
      contact_group = #{record.contactGroup,jdbcType=VARCHAR},
      mail_body = #{record.mailBody,jdbcType=VARCHAR},
      alert_tag = #{record.alertTag,jdbcType=VARCHAR},
      create_person = #{record.createPerson,jdbcType=CHAR},
      create_date = #{record.createDate,jdbcType=TIMESTAMP},
      update_person = #{record.updatePerson,jdbcType=CHAR},
      update_date = #{record.updateDate,jdbcType=TIMESTAMP}
    <if test="_parameter != null">
      <include refid="Update_By_Example_Where_Clause" />
    </if>
  </update>
  <update id="updateByPrimaryKeySelective" parameterType="job.sfcommon.dataaccess.entity.looponexcore.SlgTagMaster">
    <!--
      WARNING - @mbg.generated
      This element is automatically generated by MyBatis Generator, do not modify.
    -->
    update public.slg_tag_master
    <set>
      <if test="dispOrder != null">
        disp_order = #{dispOrder,jdbcType=INTEGER},
      </if>
      <if test="dcsTagItem != null">
        dcs_tag_item = #{dcsTagItem,jdbcType=VARCHAR},
      </if>
      <if test="comment1 != null">
        comment1 = #{comment1,jdbcType=VARCHAR},
      </if>
      <if test="stnName != null">
        stn_name = #{stnName,jdbcType=VARCHAR},
      </if>
      <if test="unitDcs != null">
        unit_dcs = #{unitDcs,jdbcType=VARCHAR},
      </if>
      <if test="unitComputer != null">
        unit_computer = #{unitComputer,jdbcType=VARCHAR},
      </if>
      <if test="multiplier != null">
        multiplier = #{multiplier,jdbcType=INTEGER},
      </if>
      <if test="dp != null">
        dp = #{dp,jdbcType=INTEGER},
      </if>
      <if test="upperValue != null">
        upper_value = #{upperValue,jdbcType=DOUBLE},
      </if>
      <if test="lowerValue != null">
        lower_value = #{lowerValue,jdbcType=DOUBLE},
      </if>
      <if test="csxl != null">
        csxl = #{csxl,jdbcType=VARCHAR},
      </if>
      <if test="collectGroupNo != null">
        collect_group_no = #{collectGroupNo,jdbcType=INTEGER},
      </if>
      <if test="historyGroupNo != null">
        history_group_no = #{historyGroupNo,jdbcType=INTEGER},
      </if>
      <if test="lastvalueHoldFlag != null">
        lastvalue_hold_flag = #{lastvalueHoldFlag,jdbcType=INTEGER},
      </if>
      <if test="collectStopFlag != null">
        collect_stop_flag = #{collectStopFlag,jdbcType=INTEGER},
      </if>
      <if test="note1 != null">
        note1 = #{note1,jdbcType=VARCHAR},
      </if>
      <if test="note2 != null">
        note2 = #{note2,jdbcType=VARCHAR},
      </if>
      <if test="note3 != null">
        note3 = #{note3,jdbcType=VARCHAR},
      </if>
      <if test="note4 != null">
        note4 = #{note4,jdbcType=VARCHAR},
      </if>
      <if test="note5 != null">
        note5 = #{note5,jdbcType=VARCHAR},
      </if>
      <if test="note6 != null">
        note6 = #{note6,jdbcType=VARCHAR},
      </if>
      <if test="note7 != null">
        note7 = #{note7,jdbcType=VARCHAR},
      </if>
      <if test="note8 != null">
        note8 = #{note8,jdbcType=VARCHAR},
      </if>
      <if test="note9 != null">
        note9 = #{note9,jdbcType=VARCHAR},
      </if>
      <if test="note10 != null">
        note10 = #{note10,jdbcType=VARCHAR},
      </if>
      <if test="startAddress != null">
        start_address = #{startAddress,jdbcType=INTEGER},
      </if>
      <if test="modbusDataType != null">
        modbus_data_type = #{modbusDataType,jdbcType=VARCHAR},
      </if>
      <if test="modbusStringSize != null">
        modbus_string_size = #{modbusStringSize,jdbcType=INTEGER},
      </if>
      <if test="hi != null">
        hi = #{hi,jdbcType=DOUBLE},
      </if>
      <if test="lo != null">
        lo = #{lo,jdbcType=DOUBLE},
      </if>
      <if test="rateChangeFlag != null">
        rate_change_flag = #{rateChangeFlag,jdbcType=INTEGER},
      </if>
      <if test="changeVolume != null">
        change_volume = #{changeVolume,jdbcType=DOUBLE},
      </if>
      <if test="hh != null">
        hh = #{hh,jdbcType=DOUBLE},
      </if>
      <if test="ll != null">
        ll = #{ll,jdbcType=DOUBLE},
      </if>
      <if test="alertMessage != null">
        alert_message = #{alertMessage,jdbcType=VARCHAR},
      </if>
      <if test="checkCycle != null">
        check_cycle = #{checkCycle,jdbcType=VARCHAR},
      </if>
      <if test="contactGroup != null">
        contact_group = #{contactGroup,jdbcType=VARCHAR},
      </if>
      <if test="mailBody != null">
        mail_body = #{mailBody,jdbcType=VARCHAR},
      </if>
      <if test="alertTag != null">
        alert_tag = #{alertTag,jdbcType=VARCHAR},
      </if>
      <if test="createPerson != null">
        create_person = #{createPerson,jdbcType=CHAR},
      </if>
      <if test="createDate != null">
        create_date = #{createDate,jdbcType=TIMESTAMP},
      </if>
      <if test="updatePerson != null">
        update_person = #{updatePerson,jdbcType=CHAR},
      </if>
      <if test="updateDate != null">
        update_date = #{updateDate,jdbcType=TIMESTAMP},
      </if>
    </set>
    where lcode = #{lcode,jdbcType=VARCHAR}
  </update>
  <update id="updateByPrimaryKey" parameterType="job.sfcommon.dataaccess.entity.looponexcore.SlgTagMaster">
    <!--
      WARNING - @mbg.generated
      This element is automatically generated by MyBatis Generator, do not modify.
    -->
    update public.slg_tag_master
    set disp_order = #{dispOrder,jdbcType=INTEGER},
      dcs_tag_item = #{dcsTagItem,jdbcType=VARCHAR},
      comment1 = #{comment1,jdbcType=VARCHAR},
      stn_name = #{stnName,jdbcType=VARCHAR},
      unit_dcs = #{unitDcs,jdbcType=VARCHAR},
      unit_computer = #{unitComputer,jdbcType=VARCHAR},
      multiplier = #{multiplier,jdbcType=INTEGER},
      dp = #{dp,jdbcType=INTEGER},
      upper_value = #{upperValue,jdbcType=DOUBLE},
      lower_value = #{lowerValue,jdbcType=DOUBLE},
      csxl = #{csxl,jdbcType=VARCHAR},
      collect_group_no = #{collectGroupNo,jdbcType=INTEGER},
      history_group_no = #{historyGroupNo,jdbcType=INTEGER},
      lastvalue_hold_flag = #{lastvalueHoldFlag,jdbcType=INTEGER},
      collect_stop_flag = #{collectStopFlag,jdbcType=INTEGER},
      note1 = #{note1,jdbcType=VARCHAR},
      note2 = #{note2,jdbcType=VARCHAR},
      note3 = #{note3,jdbcType=VARCHAR},
      note4 = #{note4,jdbcType=VARCHAR},
      note5 = #{note5,jdbcType=VARCHAR},
      note6 = #{note6,jdbcType=VARCHAR},
      note7 = #{note7,jdbcType=VARCHAR},
      note8 = #{note8,jdbcType=VARCHAR},
      note9 = #{note9,jdbcType=VARCHAR},
      note10 = #{note10,jdbcType=VARCHAR},
      start_address = #{startAddress,jdbcType=INTEGER},
      modbus_data_type = #{modbusDataType,jdbcType=VARCHAR},
      modbus_string_size = #{modbusStringSize,jdbcType=INTEGER},
      hi = #{hi,jdbcType=DOUBLE},
      lo = #{lo,jdbcType=DOUBLE},
      rate_change_flag = #{rateChangeFlag,jdbcType=INTEGER},
      change_volume = #{changeVolume,jdbcType=DOUBLE},
      hh = #{hh,jdbcType=DOUBLE},
      ll = #{ll,jdbcType=DOUBLE},
      alert_message = #{alertMessage,jdbcType=VARCHAR},
      check_cycle = #{checkCycle,jdbcType=VARCHAR},
      contact_group = #{contactGroup,jdbcType=VARCHAR},
      mail_body = #{mailBody,jdbcType=VARCHAR},
      alert_tag = #{alertTag,jdbcType=VARCHAR},
      create_person = #{createPerson,jdbcType=CHAR},
      create_date = #{createDate,jdbcType=TIMESTAMP},
      update_person = #{updatePerson,jdbcType=CHAR},
      update_date = #{updateDate,jdbcType=TIMESTAMP}
    where lcode = #{lcode,jdbcType=VARCHAR}
  </update>
</mapper>