<?xml version="1.0" encoding="UTF-8"?>
<!DOCTYPE mapper PUBLIC "-//mybatis.org//DTD Mapper 3.0//EN" "http://mybatis.org/dtd/mybatis-3-mapper.dtd">
<mapper namespace="job.sfcommon.dataaccess.mapper.looponexcore.MSubsystemOpcMapper">
  <resultMap id="BaseResultMap" type="job.sfcommon.dataaccess.entity.looponexcore.MSubsystemOpc">
    <!--
      WARNING - @mbg.generated
      This element is automatically generated by MyBatis Generator, do not modify.
    -->
    <id column="subsystem_id" jdbcType="VARCHAR" property="subsystemId" />
    <result column="ex_opc_name" jdbcType="VARCHAR" property="exOpcName" />
    <result column="ex_opc_port" jdbcType="INTEGER" property="exOpcPort" />
    <result column="ex_opc_da_progid" jdbcType="VARCHAR" property="exOpcDaProgid" />
    <result column="server_address" jdbcType="VARCHAR" property="serverAddress" />
  </resultMap>
  <sql id="Example_Where_Clause">
    <!--
      WARNING - @mbg.generated
      This element is automatically generated by MyBatis Generator, do not modify.
    -->
    <where>
      <foreach collection="oredCriteria" item="criteria" separator="or">
        <if test="criteria.valid">
          <trim prefix="(" prefixOverrides="and" suffix=")">
            <foreach collection="criteria.criteria" item="criterion">
              <choose>
                <when test="criterion.noValue">
                  and ${criterion.condition}
                </when>
                <when test="criterion.singleValue">
                  and ${criterion.condition} #{criterion.value}
                </when>
                <when test="criterion.betweenValue">
                  and ${criterion.condition} #{criterion.value} and #{criterion.secondValue}
                </when>
                <when test="criterion.listValue">
                  and ${criterion.condition}
                  <foreach close=")" collection="criterion.value" item="listItem" open="(" separator=",">
                    #{listItem}
                  </foreach>
                </when>
              </choose>
            </foreach>
          </trim>
        </if>
      </foreach>
    </where>
  </sql>
  <sql id="Update_By_Example_Where_Clause">
    <!--
      WARNING - @mbg.generated
      This element is automatically generated by MyBatis Generator, do not modify.
    -->
    <where>
      <foreach collection="example.oredCriteria" item="criteria" separator="or">
        <if test="criteria.valid">
          <trim prefix="(" prefixOverrides="and" suffix=")">
            <foreach collection="criteria.criteria" item="criterion">
              <choose>
                <when test="criterion.noValue">
                  and ${criterion.condition}
                </when>
                <when test="criterion.singleValue">
                  and ${criterion.condition} #{criterion.value}
                </when>
                <when test="criterion.betweenValue">
                  and ${criterion.condition} #{criterion.value} and #{criterion.secondValue}
                </when>
                <when test="criterion.listValue">
                  and ${criterion.condition}
                  <foreach close=")" collection="criterion.value" item="listItem" open="(" separator=",">
                    #{listItem}
                  </foreach>
                </when>
              </choose>
            </foreach>
          </trim>
        </if>
      </foreach>
    </where>
  </sql>
  <sql id="Base_Column_List">
    <!--
      WARNING - @mbg.generated
      This element is automatically generated by MyBatis Generator, do not modify.
    -->
    subsystem_id, ex_opc_name, ex_opc_port, ex_opc_da_progid, server_address
  </sql>
  <select id="selectByExample" parameterType="job.sfcommon.dataaccess.entity.looponexcore.MSubsystemOpcExample" resultMap="BaseResultMap">
    <!--
      WARNING - @mbg.generated
      This element is automatically generated by MyBatis Generator, do not modify.
    -->
    select
    <if test="distinct">
      distinct
    </if>
    <include refid="Base_Column_List" />
    from public.m_subsystem_opc
    <if test="_parameter != null">
      <include refid="Example_Where_Clause" />
    </if>
    <if test="orderByClause != null">
      order by ${orderByClause}
    </if>
  </select>
  <select id="selectByPrimaryKey" parameterType="java.lang.String" resultMap="BaseResultMap">
    <!--
      WARNING - @mbg.generated
      This element is automatically generated by MyBatis Generator, do not modify.
    -->
    select 
    <include refid="Base_Column_List" />
    from public.m_subsystem_opc
    where subsystem_id = #{subsystemId,jdbcType=VARCHAR}
  </select>
  <delete id="deleteByPrimaryKey" parameterType="java.lang.String">
    <!--
      WARNING - @mbg.generated
      This element is automatically generated by MyBatis Generator, do not modify.
    -->
    delete from public.m_subsystem_opc
    where subsystem_id = #{subsystemId,jdbcType=VARCHAR}
  </delete>
  <delete id="deleteByExample" parameterType="job.sfcommon.dataaccess.entity.looponexcore.MSubsystemOpcExample">
    <!--
      WARNING - @mbg.generated
      This element is automatically generated by MyBatis Generator, do not modify.
    -->
    delete from public.m_subsystem_opc
    <if test="_parameter != null">
      <include refid="Example_Where_Clause" />
    </if>
  </delete>
  <insert id="insert" parameterType="job.sfcommon.dataaccess.entity.looponexcore.MSubsystemOpc">
    <!--
      WARNING - @mbg.generated
      This element is automatically generated by MyBatis Generator, do not modify.
    -->
    insert into public.m_subsystem_opc (subsystem_id, ex_opc_name, ex_opc_port, 
      ex_opc_da_progid, server_address)
    values (#{subsystemId,jdbcType=VARCHAR}, #{exOpcName,jdbcType=VARCHAR}, #{exOpcPort,jdbcType=INTEGER}, 
      #{exOpcDaProgid,jdbcType=VARCHAR}, #{serverAddress,jdbcType=VARCHAR})
  </insert>
  <insert id="insertSelective" parameterType="job.sfcommon.dataaccess.entity.looponexcore.MSubsystemOpc">
    <!--
      WARNING - @mbg.generated
      This element is automatically generated by MyBatis Generator, do not modify.
    -->
    insert into public.m_subsystem_opc
    <trim prefix="(" suffix=")" suffixOverrides=",">
      <if test="subsystemId != null">
        subsystem_id,
      </if>
      <if test="exOpcName != null">
        ex_opc_name,
      </if>
      <if test="exOpcPort != null">
        ex_opc_port,
      </if>
      <if test="exOpcDaProgid != null">
        ex_opc_da_progid,
      </if>
      <if test="serverAddress != null">
        server_address,
      </if>
    </trim>
    <trim prefix="values (" suffix=")" suffixOverrides=",">
      <if test="subsystemId != null">
        #{subsystemId,jdbcType=VARCHAR},
      </if>
      <if test="exOpcName != null">
        #{exOpcName,jdbcType=VARCHAR},
      </if>
      <if test="exOpcPort != null">
        #{exOpcPort,jdbcType=INTEGER},
      </if>
      <if test="exOpcDaProgid != null">
        #{exOpcDaProgid,jdbcType=VARCHAR},
      </if>
      <if test="serverAddress != null">
        #{serverAddress,jdbcType=VARCHAR},
      </if>
    </trim>
  </insert>
  <select id="countByExample" parameterType="job.sfcommon.dataaccess.entity.looponexcore.MSubsystemOpcExample" resultType="java.lang.Long">
    <!--
      WARNING - @mbg.generated
      This element is automatically generated by MyBatis Generator, do not modify.
    -->
    select count(*) from public.m_subsystem_opc
    <if test="_parameter != null">
      <include refid="Example_Where_Clause" />
    </if>
  </select>
  <update id="updateByExampleSelective" parameterType="map">
    <!--
      WARNING - @mbg.generated
      This element is automatically generated by MyBatis Generator, do not modify.
    -->
    update public.m_subsystem_opc
    <set>
      <if test="record.subsystemId != null">
        subsystem_id = #{record.subsystemId,jdbcType=VARCHAR},
      </if>
      <if test="record.exOpcName != null">
        ex_opc_name = #{record.exOpcName,jdbcType=VARCHAR},
      </if>
      <if test="record.exOpcPort != null">
        ex_opc_port = #{record.exOpcPort,jdbcType=INTEGER},
      </if>
      <if test="record.exOpcDaProgid != null">
        ex_opc_da_progid = #{record.exOpcDaProgid,jdbcType=VARCHAR},
      </if>
      <if test="record.serverAddress != null">
        server_address = #{record.serverAddress,jdbcType=VARCHAR},
      </if>
    </set>
    <if test="_parameter != null">
      <include refid="Update_By_Example_Where_Clause" />
    </if>
  </update>
  <update id="updateByExample" parameterType="map">
    <!--
      WARNING - @mbg.generated
      This element is automatically generated by MyBatis Generator, do not modify.
    -->
    update public.m_subsystem_opc
    set subsystem_id = #{record.subsystemId,jdbcType=VARCHAR},
      ex_opc_name = #{record.exOpcName,jdbcType=VARCHAR},
      ex_opc_port = #{record.exOpcPort,jdbcType=INTEGER},
      ex_opc_da_progid = #{record.exOpcDaProgid,jdbcType=VARCHAR},
      server_address = #{record.serverAddress,jdbcType=VARCHAR}
    <if test="_parameter != null">
      <include refid="Update_By_Example_Where_Clause" />
    </if>
  </update>
  <update id="updateByPrimaryKeySelective" parameterType="job.sfcommon.dataaccess.entity.looponexcore.MSubsystemOpc">
    <!--
      WARNING - @mbg.generated
      This element is automatically generated by MyBatis Generator, do not modify.
    -->
    update public.m_subsystem_opc
    <set>
      <if test="exOpcName != null">
        ex_opc_name = #{exOpcName,jdbcType=VARCHAR},
      </if>
      <if test="exOpcPort != null">
        ex_opc_port = #{exOpcPort,jdbcType=INTEGER},
      </if>
      <if test="exOpcDaProgid != null">
        ex_opc_da_progid = #{exOpcDaProgid,jdbcType=VARCHAR},
      </if>
      <if test="serverAddress != null">
        server_address = #{serverAddress,jdbcType=VARCHAR},
      </if>
    </set>
    where subsystem_id = #{subsystemId,jdbcType=VARCHAR}
  </update>
  <update id="updateByPrimaryKey" parameterType="job.sfcommon.dataaccess.entity.looponexcore.MSubsystemOpc">
    <!--
      WARNING - @mbg.generated
      This element is automatically generated by MyBatis Generator, do not modify.
    -->
    update public.m_subsystem_opc
    set ex_opc_name = #{exOpcName,jdbcType=VARCHAR},
      ex_opc_port = #{exOpcPort,jdbcType=INTEGER},
      ex_opc_da_progid = #{exOpcDaProgid,jdbcType=VARCHAR},
      server_address = #{serverAddress,jdbcType=VARCHAR}
    where subsystem_id = #{subsystemId,jdbcType=VARCHAR}
  </update>
</mapper>